httpbenchw/__init__.py
httpbenchw/main.py
httpbenchw-0.1.2.dist-info/licenses/LICENSE
httpbenchw-0.1.2.dist-info/METADATA
httpbenchw-0.1.2.dist-info/WHEEL
httpbenchw-0.1.2.dist-info/entry_points.txt
httpbenchw-0.1.2.dist-info/top_level.txt
httpbenchw-0.1.2.dist-info/RECORD
