Metadata-Version: 2.4
Name: httpbenchw
Version: 0.1.2
Summary: Lightweight HTTP load testing tool.
License-File: LICENSE
Requires-Dist: requests
Dynamic: license-file
